COPYING
MANIFEST.in
README.md
README.rst
caatinga.conf.sample
ez_setup.py
setup.py
caatinga/__init__.py
caatinga/caat_main.py
caatinga/lineaverages.py
caatinga/lscaat_main.py
caatinga.egg-info/PKG-INFO
caatinga.egg-info/SOURCES.txt
caatinga.egg-info/dependency_links.txt
caatinga.egg-info/entry_points.txt
caatinga.egg-info/top_level.txt
caatinga/caat/__init__.py
caatinga/caat/backup.py
caatinga/caat/maintenance.py
caatinga/caat/organizer.py
caatinga/core/__init__.py
caatinga/core/args.py
caatinga/core/functions.py
caatinga/core/settings.py
caatinga/core/validation.py
caatinga/lscaat/__init__.py
caatinga/lscaat/changes.py
caatinga/lscaat/diff.py
caatinga/lscaat/help.py
caatinga/lscaat/info.py
caatinga/lscaat/listFiles.py
caatinga/lscaat/remove.py
caatinga/lscaat/restore.py
docs/caat.1.gz
docs/caatinga.conf.5.gz
docs/lscaat.1.gz